{
  "projectName": "tic-coder-lite",
  "rootPath": "C:\\git\\tic-coder-lite",
  "generatedAt": "2026-04-30T23:12:27.888Z",
  "stack": [
    {
      "id": "java-maven",
      "name": "Java / Maven",
      "detected": false,
      "evidence": []
    },
    {
      "id": "java-gradle",
      "name": "Java / Gradle",
      "detected": false,
      "evidence": []
    },
    {
      "id": "node",
      "name": "Node.js",
      "detected": true,
      "evidence": [
        "package.json"
      ]
    },
    {
      "id": "react",
      "name": "React",
      "detected": false,
      "evidence": []
    },
    {
      "id": "angular",
      "name": "Angular",
      "detected": false,
      "evidence": []
    },
    {
      "id": "next",
      "name": "Next.js",
      "detected": false,
      "evidence": []
    },
    {
      "id": "vite",
      "name": "Vite",
      "detected": false,
      "evidence": []
    },
    {
      "id": "spring-boot",
      "name": "Spring Boot",
      "detected": false,
      "evidence": []
    },
    {
      "id": "docker",
      "name": "Docker Compose",
      "detected": false,
      "evidence": []
    },
    {
      "id": "database",
      "name": "SQL / Database",
      "detected": false,
      "evidence": []
    }
  ],
  "javaSpring": {
    "detected": false,
    "annotations": {},
    "files": [],
    "countsByKind": {
      "controller": 0,
      "service": 0,
      "repository": 0,
      "entity": 0,
      "dto": 0,
      "config": 0,
      "security": 0,
      "unknown": 0
    }
  },
  "typeScript": {
    "detected": true,
    "packageManager": "npm",
    "frameworks": [
      "Node.js"
    ],
    "dependencies": {},
    "devDependencies": {
      "@types/node": "^20.14.10",
      "@types/vscode": "^1.92.0",
      "typescript": "^5.5.4"
    },
    "sourceFiles": {
      "total": 37,
      "components": [],
      "pages": [],
      "services": [],
      "configs": []
    }
  },
  "modules": [
    {
      "kind": "controller",
      "files": []
    },
    {
      "kind": "service",
      "files": []
    },
    {
      "kind": "repository",
      "files": []
    },
    {
      "kind": "entity",
      "files": []
    },
    {
      "kind": "dto",
      "files": []
    },
    {
      "kind": "config",
      "files": []
    },
    {
      "kind": "security",
      "files": []
    },
    {
      "kind": "unknown",
      "files": [
        "src/commands/analyzeProject.ts",
        "src/commands/enhanceWithLocalAi.ts",
        "src/commands/exportAgentsMd.ts",
        "src/commands/generateAgentContext.ts",
        "src/commands/openOverview.ts",
        "src/exporters/generateAgentContextMd.ts",
        "src/exporters/generateConfidenceReportMd.ts",
        "src/exporters/generateQuestionsMd.ts",
        "src/exporters/writeTicCodeFolder.ts",
        "src/extension.ts",
        "src/local-ai/checkOllamaStatus.ts",
        "src/local-ai/enhanceAgentContext.ts",
        "src/local-ai/enhanceModuleSummary.ts",
        "src/local-ai/ollamaClient.ts",
        "src/reversa-adapter/detectEngines.ts",
        "src/reversa-adapter/engineTypes.ts",
        "src/reversa-adapter/exportForEngines.ts",
        "src/reversa-adapter/generateAgentsMd.ts",
        "src/reversa-adapter/generateClaudeMd.ts",
        "src/reversa-adapter/generateCopilotInstructions.ts",
        "src/reversa-adapter/generateCursorRules.ts",
        "src/reversa-adapter/generateGeminiMd.ts",
        "src/reversa-adapter/safeWriter.ts",
        "src/scanner/buildGraph.ts",
        "src/scanner/detectJavaSpring.ts",
        "src/scanner/detectRisks.ts",
        "src/scanner/detectStack.ts",
        "src/scanner/detectTypeScriptProject.ts",
        "src/scanner/ignoreRules.ts",
        "src/scanner/parseImports.ts",
        "src/scanner/scanFiles.ts",
        "src/scanner/scanWorkspace.ts",
        "src/types.ts",
        "src/webview/graphRenderer.ts",
        "src/webview/overviewHtml.ts",
        "src/webview/overviewPanel.ts",
        "src/webview/webviewAssets.ts"
      ]
    }
  ],
  "database": {
    "detected": false,
    "evidence": []
  },
  "docker": {
    "detected": false,
    "evidence": []
  }
}
